numbersprotocol_capture/__init__.py
numbersprotocol_capture/client.py
numbersprotocol_capture/crypto.py
numbersprotocol_capture/errors.py
numbersprotocol_capture/py.typed
numbersprotocol_capture/types.py
numbersprotocol_capture/verify.py
numbersprotocol_capture_sdk-0.2.1.dist-info/METADATA
numbersprotocol_capture_sdk-0.2.1.dist-info/WHEEL
numbersprotocol_capture_sdk-0.2.1.dist-info/RECORD
