Metadata-Version: 2.4
Name: numbersprotocol-capture-sdk
Version: 0.2.1
Summary: Python SDK for Numbers Protocol Capture API
Project-URL: Homepage, https://github.com/numbersprotocol/capture-sdk
Project-URL: Documentation, https://github.com/numbersprotocol/capture-sdk#readme
Project-URL: Repository, https://github.com/numbersprotocol/capture-sdk
Project-URL: Issues, https://github.com/numbersprotocol/capture-sdk/issues
Author: Numbers Protocol
License-Expression: MIT
Keywords: blockchain,capture,digital-assets,numbers-protocol,provenance,web3
Classifier: Development Status :: 4 - Beta
Classifier: Intended Audience :: Developers
Classifier: License :: OSI Approved :: MIT License
Classifier: Operating System :: OS Independent
Classifier: Programming Language :: Python :: 3
Classifier: Programming Language :: Python :: 3.10
Classifier: Programming Language :: Python :: 3.11
Classifier: Programming Language :: Python :: 3.12
Classifier: Programming Language :: Python :: 3.13
Classifier: Topic :: Software Development :: Libraries :: Python Modules
Classifier: Typing :: Typed
Requires-Python: >=3.10
Requires-Dist: eth-account>=0.10.0
Requires-Dist: httpx>=0.25.0
Provides-Extra: dev
Requires-Dist: mypy>=1.0.0; extra == 'dev'
Requires-Dist: pytest-asyncio>=0.21.0; extra == 'dev'
Requires-Dist: pytest-cov>=4.0.0; extra == 'dev'
Requires-Dist: pytest>=7.0.0; extra == 'dev'
Requires-Dist: respx>=0.20.0; extra == 'dev'
Requires-Dist: ruff>=0.1.0; extra == 'dev'
